pudzu/patterns/__init__.py
pudzu/patterns/patterns.py
pudzu_patterns-0.9.3.dist-info/METADATA
pudzu_patterns-0.9.3.dist-info/WHEEL
pudzu_patterns-0.9.3.dist-info/entry_points.txt
pudzu_patterns-0.9.3.dist-info/RECORD
