Metadata-Version: 2.1
Name: pudzu-patterns
Version: 0.9.3
Summary: NFA-based pattern matcher supporting novel operations and modifiers
Home-page: https://github.com/Udzu/pudzu-packages/pudzu-patterns/
License: MIT
Keywords: pudzu,regex
Author: Uri Granta
Author-email: uri.granta+python@gmail.com
Requires-Python: >=3.7,<4.0
Classifier: License :: OSI Approved :: MIT License
Classifier: Operating System :: OS Independent
Classifier: Programming Language :: Python :: 3
Classifier: Programming Language :: Python :: 3.7
Classifier: Programming Language :: Python :: 3.8
Classifier: Programming Language :: Python :: 3.9
Classifier: Programming Language :: Python :: 3.10
Classifier: Programming Language :: Python :: 3.11
Classifier: Programming Language :: Python :: 3.12
Requires-Dist: graphviz (>=0.13.2,<0.14.0)
Requires-Dist: pudzu-utils (>=0.9.3,<0.10.0)
Requires-Dist: pyparsing (>=3.0,<4.0)
